swagger_coverage/__init__.py
swagger_coverage/scripts/swagger_report.py
swagger_coverage/src/__init__.py
swagger_coverage/src/check_data.py
swagger_coverage/src/coverage.py
swagger_coverage/src/deco.py
swagger_coverage/src/files.py
swagger_coverage/src/logger.py
swagger_coverage/src/models/__init__.py
swagger_coverage/src/models/stats.py
swagger_coverage/src/models/swagger_data.py
swagger_coverage/src/prepare_data.py
swagger_coverage/src/report/__init__.py
swagger_coverage/src/report/html/__init__.py
swagger_coverage/src/report/html/accordion.py
swagger_coverage/src/report/html/body.py
swagger_coverage/src/report/html/btn_group.py
swagger_coverage/src/report/html/colors.py
swagger_coverage/src/report/html/constants.py
swagger_coverage/src/report/html/h2.py
swagger_coverage/src/report/html/head.py
swagger_coverage/src/report/html/href.py
swagger_coverage/src/report/html/html_report.py
swagger_coverage/src/report/html/models.py
swagger_coverage/src/report/html/navbar.py
swagger_coverage/src/report/html/p.py
swagger_coverage/src/report/html/prepare_data.py
swagger_coverage/src/report/html/progress.py
swagger_coverage/src/report/html/scripts.py
swagger_coverage/src/report/html/table.py
swagger_coverage/src/report/plain/__init__.py
swagger_coverage/src/report/plain/plain_report.py
swagger_coverage/src/report/report.py
swagger_coverage/src/requests.py
swagger_coverage/src/results/__init__.py
swagger_coverage/src/results/load_results.py
swagger_coverage/src/results/swagger_diff.py
swagger_coverage/src/results/swagger_results.py
swagger_coverage/src/results/swagger_summary.py
swagger_coverage/src/singltone_like.py
swagger_coverage/src/utils.py
test_swagger_coverage-2.1.62.dist-info/LICENSE
test_swagger_coverage-2.1.62.dist-info/METADATA
test_swagger_coverage-2.1.62.dist-info/WHEEL
test_swagger_coverage-2.1.62.dist-info/entry_points.txt
test_swagger_coverage-2.1.62.dist-info/RECORD
