Metadata-Version: 2.1
Name: test-swagger-coverage
Version: 2.1.62
Summary: Swagger coverage for API tests
Home-page: https://github.com/berpress/swagger-coverage
Author: alexanderlozovoy
Author-email: berpress@gmail.com
Requires-Python: >=3.8,<4.0
Classifier: Programming Language :: Python :: 3
Classifier: Programming Language :: Python :: 3.8
Classifier: Programming Language :: Python :: 3.9
Classifier: Programming Language :: Python :: 3.10
Classifier: Programming Language :: Python :: 3.11
Requires-Dist: pyyaml (>=6.0,<7.0)
Requires-Dist: requests (>=2.28.2,<3.0.0)
Project-URL: Repository, https://github.com/berpress/swagger-coverage
